pyguiadapterlite/.gitignore
pyguiadapterlite/__init__.py
pyguiadapterlite/_assets/images/info.png
pyguiadapterlite/_assets/locales/en_US/LC_MESSAGES/pyguiadapterlite.mo
pyguiadapterlite/_assets/locales/en_US.po
pyguiadapterlite/_assets/locales/pyguiadapterlite.pot
pyguiadapterlite/_assets/locales/zh_CN/LC_MESSAGES/pyguiadapterlite.mo
pyguiadapterlite/_assets/locales/zh_CN.po
pyguiadapterlite/_messages.py
pyguiadapterlite/assets.py
pyguiadapterlite/components/__init__.py
pyguiadapterlite/components/colorlabel.py
pyguiadapterlite/components/combo.py
pyguiadapterlite/components/common.py
pyguiadapterlite/components/dialog.py
pyguiadapterlite/components/listview.py
pyguiadapterlite/components/menus.py
pyguiadapterlite/components/multiplechoice.py
pyguiadapterlite/components/paramtabview.py
pyguiadapterlite/components/scrollarea.py
pyguiadapterlite/components/singlechoice.py
pyguiadapterlite/components/tabview.py
pyguiadapterlite/components/termview.py
pyguiadapterlite/components/textview.py
pyguiadapterlite/components/toast.py
pyguiadapterlite/components/tooltip.py
pyguiadapterlite/components/valuewidget.py
pyguiadapterlite/core/__init__.py
pyguiadapterlite/core/adapter.py
pyguiadapterlite/core/context.py
pyguiadapterlite/core/fn.py
pyguiadapterlite/core/fnparser.py
pyguiadapterlite/core/registry.py
pyguiadapterlite/core/threaded.py
pyguiadapterlite/core/ucontext.py
pyguiadapterlite/i18n.py
pyguiadapterlite/pathutils.py
pyguiadapterlite/types/__init__.py
pyguiadapterlite/types/booleans/__init__.py
pyguiadapterlite/types/booleans/boolcheck.py
pyguiadapterlite/types/booleans/common.py
pyguiadapterlite/types/choices/__init__.py
pyguiadapterlite/types/choices/enumchoice.py
pyguiadapterlite/types/choices/loosechoice.py
pyguiadapterlite/types/choices/multichoice.py
pyguiadapterlite/types/choices/singlechoice.py
pyguiadapterlite/types/colors/__init__.py
pyguiadapterlite/types/colors/color.py
pyguiadapterlite/types/extendtypes.py
pyguiadapterlite/types/floats/__init__.py
pyguiadapterlite-0.6.11.dist-info/LICENSE
pyguiadapterlite-0.6.11.dist-info/LICENSES/docstring_parser-LICENSE.md
pyguiadapterlite-0.6.11.dist-info/LICENSES/IconPark-LICENSE.txt
pyguiadapterlite-0.6.11.dist-info/LICENSES/tomlkit-LICENSE.txt
pyguiadapterlite-0.6.11.dist-info/METADATA
pyguiadapterlite-0.6.11.dist-info/WHEEL
pyguiadapterlite-0.6.11.dist-info/RECORD
