Metadata-Version: 2.1
Name: pyguiadapterlite
Version: 0.6.11
Summary: Turn your python functions into GUI-based applications just in a few lines of code.
Home-page: https://github.com/zimolab/pyguiadapterlite
Author: zimolab
Author-email: zimolab@aliyun.com
Requires-Python: >=3.8
Classifier: Programming Language :: Python :: 3
Classifier: Programming Language :: Python :: 3.8
Classifier: Programming Language :: Python :: 3.9
Classifier: Programming Language :: Python :: 3.10
Classifier: Programming Language :: Python :: 3.11
Classifier: Programming Language :: Python :: 3.12
Requires-Dist: docstring-parser (>=0.17.0,<0.18.0)
Requires-Dist: tomlkit (>=0.13.3,<0.14.0)
Project-URL: Repository, https://github.com/zimolab/pyguiadapterlite
